<PubmedArticle><MedlineCitation Status="MEDLINE" Owner="NLM" IndexingMethod="Automated"><PMID Version="1">39437140</PMID><DateCompleted><Year>2024</Year><Month>10</Month><Day>22</Day></DateCompleted><DateRevised><Year>2024</Year><Month>10</Month><Day>22</Day></DateRevised><Article PubModel="Print-Electronic"><Journal><ISSN IssnType="Electronic">2766-5526</ISSN><JournalIssue CitedMedium="Internet"><Volume>3</Volume><Issue>11</Issue><PubDate><Year>2024</Year><Month>Nov</Month></PubDate></JournalIssue><Title>NEJM evidence</Title><ISOAbbreviation>NEJM Evid</ISOAbbreviation></Journal><ArticleTitle>Sedation in the ICU.</ArticleTitle><Pagination><StartPage>EVIDra2300347</StartPage><MedlinePgn>EVIDra2300347</MedlinePgn></Pagination><ELocationID EIdType="doi" ValidYN="Y">10.1056/EVIDra2300347</ELocationID><Abstract><AbstractText>AbstractSedation practices are key to improving intensive care unit (ICU) outcomes. Adequate treatment of pain, minimization of sedation, delirium prevention, and improved patient interaction to ensure early rehabilitation and faster ventilator liberation are evidenced-based components of ICU care. Here we review components of appropriate ICU sedation including the use of multicomponent care bundles such as the ABCDEF bundle with a focus on changes in ICU practice that followed the Covid-19 pandemic.</AbstractText></Abstract><AuthorList CompleteYN="Y"><Author ValidYN="Y"><LastName>Northam</LastName><ForeName>Kalynn A</ForeName><Initials>KA</Initials><AffiliationInfo><Affiliation>Department of Pharmacy, Massachusetts General Hospital, 55 Fruit Street, Boston, MA.</Affiliation></AffiliationInfo></Author><Author ValidYN="Y"><LastName>Phillips</LastName><ForeName>Kristy M</ForeName><Initials>KM</Initials><AffiliationInfo><Affiliation>Department of Pharmacy, Denver Health and Hospital Authority, 777 Bannock Street, Denver, CO.</Affiliation></AffiliationInfo></Author></AuthorList><Language>eng</Language><PublicationTypeList><PublicationType UI="D016428">Journal Article</PublicationType><PublicationType UI="D016454">Review</PublicationType></PublicationTypeList><ArticleDate DateType="Electronic"><Year>2024</Year><Month>10</Month><Day>22</Day></ArticleDate></Article><MedlineJournalInfo><Country>United States</Country><MedlineTA>NEJM Evid</MedlineTA><NlmUniqueID>9918317485806676</NlmUniqueID><ISSNLinking>2766-5526</ISSNLinking></MedlineJournalInfo><ChemicalList><Chemical><RegistryNumber>0</RegistryNumber><NameOfSubstance UI="D006993">Hypnotics and Sedatives</NameOfSubstance></Chemical></ChemicalList><CitationSubset>IM</CitationSubset><MeshHeadingList><MeshHeading><DescriptorName UI="D006801" MajorTopicYN="N">Humans</DescriptorName></MeshHeading><MeshHeading><DescriptorName UI="D007362" MajorTopicYN="Y">Intensive Care Units</DescriptorName></MeshHeading><MeshHeading><DescriptorName UI="D000086382" MajorTopicYN="Y">COVID-19</DescriptorName><QualifierName UI="Q000517" MajorTopicYN="N">prevention &amp; control</QualifierName></MeshHeading><MeshHeading><DescriptorName UI="D006993" MajorTopicYN="N">Hypnotics and Sedatives</DescriptorName><QualifierName UI="Q000627" MajorTopicYN="N">therapeutic use</QualifierName></MeshHeading><MeshHeading><DescriptorName UI="D003422" MajorTopicYN="N">Critical Care</DescriptorName><QualifierName UI="Q000379" MajorTopicYN="N">methods</QualifierName></MeshHeading><MeshHeading><DescriptorName UI="D016292" MajorTopicYN="N">Conscious Sedation</DescriptorName><QualifierName UI="Q000379" MajorTopicYN="N">methods</QualifierName></MeshHeading><MeshHeading><DescriptorName UI="D003693" MajorTopicYN="N">Delirium</DescriptorName><QualifierName UI="Q000517" MajorTopicYN="N">prevention &amp; control</QualifierName><QualifierName UI="Q000628" MajorTopicYN="N">therapy</QualifierName></MeshHeading></MeshHeadingList></MedlineCitation><PubmedData><History><PubMedPubDate PubStatus="medline"><Year>2024</Year><Month>10</Month><Day>22</Day><Hour>18</Hour><Minute>23</Minute></PubMedPubDate><PubMedPubDate PubStatus="pubmed"><Year>2024</Year><Month>10</Month><Day>22</Day><Hour>18</Hour><Minute>22</Minute></PubMedPubDate><PubMedPubDate PubStatus="entrez"><Year>2024</Year><Month>10</Month><Day>22</Day><Hour>14</Hour><Minute>33</Minute></PubMedPubDate></History><PublicationStatus>ppublish</PublicationStatus><ArticleIdList><ArticleId IdType="pubmed">39437140</ArticleId><ArticleId IdType="doi">10.1056/EVIDra2300347</ArticleId></ArticleIdList></PubmedData></PubmedArticle>