<PubmedArticle><MedlineCitation Status="MEDLINE" Owner="NLM" IndexingMethod="Automated"><PMID Version="1">39321313</PMID><DateCompleted><Year>2024</Year><Month>10</Month><Day>09</Day></DateCompleted><DateRevised><Year>2024</Year><Month>10</Month><Day>09</Day></DateRevised><Article PubModel="Print-Electronic"><Journal><ISSN IssnType="Electronic">1520-5118</ISSN><JournalIssue CitedMedium="Internet"><Volume>72</Volume><Issue>40</Issue><PubDate><Year>2024</Year><Month>Oct</Month><Day>09</Day></PubDate></JournalIssue><Title>Journal of agricultural and food chemistry</Title><ISOAbbreviation>J Agric Food Chem</ISOAbbreviation></Journal><ArticleTitle>Study on the Bioactivity, Toxicity, Stereoselective Fate, and Risk Assessment of Chiral Fungicide Isopyrazam in Five Kinds of Fruits and Vegetables.</ArticleTitle><Pagination><StartPage>22073</StartPage><EndPage>22081</EndPage><MedlinePgn>22073-22081</MedlinePgn></Pagination><ELocationID EIdType="doi" ValidYN="Y">10.1021/acs.jafc.4c05937</ELocationID><Abstract><AbstractText>Isopyrazam (IPZ) is a new chiral fungicide. For bioactivity, there was a 3.37-1578 times difference among the four stereoisomers. For <i>Alternaria alternata</i> and <i>Phoma multirostrata</i>, <i>cis</i>-(1<i>S</i>,4<i>R</i>,9<i>S</i>)<i>-</i>IPZ had the greatest activity. Using <i>cis</i>-IPZ might improve the efficacy and reduce the dosage of the racemate by 54.7-72.2% for <i>A. alternata</i> and <i>P. multirostrata</i>. To zebrafish, <i>trans</i>-IPZ showed the highest acute toxicity (LC<sub>50</sub>, 0.096 mg/L). The degradation half-lives of IPZ stereoisomers in the five crops ranged from 3.50 to 15.2 days. <i>Cis</i>-IPZ was preferentially degraded in grape, pear, and celery. The residual concentrations of IPZ in grape and celery were still higher than the maximum residue limit, and the acute and chronic dietary intake risks of IPZ in celery were unacceptable (RQ<sub>a</sub>: 146-250%, HQ: 117-200%), which were worthy of further researching. Based on the research results, it is safer and more reasonable to use IPZ in the form of a racemate with a high ratio of <i>cis</i>-IPZ.</AbstractText></Abstract><AuthorList CompleteYN="Y"><Author ValidYN="Y"><LastName>Wang</LastName><ForeName>Xinquan</ForeName><Initials>X</Initials><Identifier Source="ORCID">0000-0002-3987-2020</Identifier><AffiliationInfo><Affiliation>State Key Laboratory for Managing Biotic and Chemical Threats to the Quality and Safety of Agro-Products/Key Laboratory of Detection for Pesticide Residues and Control of Zhejiang, Institute of Agro-Product Safety and Nutrition, Zhejiang Academy of Agricultural Sciences, Hangzhou 310021, P. R. China.</Affiliation></AffiliationInfo><AffiliationInfo><Affiliation>Agricultural Ministry Key Laboratory for Pesticide Residue Detection, Hangzhou 310021, P. R. China.</Affiliation></AffiliationInfo></Author><Author ValidYN="Y"><LastName>Diao</LastName><ForeName>Ziyang</ForeName><Initials>Z</Initials><AffiliationInfo><Affiliation>State Key Laboratory for Managing Biotic and Chemical Threats to the Quality and Safety of Agro-Products/Key Laboratory of Detection for Pesticide Residues and Control of Zhejiang, Institute of Agro-Product Safety and Nutrition, Zhejiang Academy of Agricultural Sciences, Hangzhou 310021, P. R. China.</Affiliation></AffiliationInfo><AffiliationInfo><Affiliation>Agricultural Ministry Key Laboratory for Pesticide Residue Detection, Hangzhou 310021, P. R. China.</Affiliation></AffiliationInfo></Author><Author ValidYN="Y"><LastName>Cang</LastName><ForeName>Tao</ForeName><Initials>T</Initials><AffiliationInfo><Affiliation>State Key Laboratory for Managing Biotic and Chemical Threats to the Quality and Safety of Agro-Products/Key Laboratory of Detection for Pesticide Residues and Control of Zhejiang, Institute of Agro-Product Safety and Nutrition, Zhejiang Academy of Agricultural Sciences, Hangzhou 310021, P. R. China.</Affiliation></AffiliationInfo><AffiliationInfo><Affiliation>Agricultural Ministry Key Laboratory for Pesticide Residue Detection, Hangzhou 310021, P. R. China.</Affiliation></AffiliationInfo></Author><Author ValidYN="Y"><LastName>Zhao</LastName><ForeName>Huiyu</ForeName><Initials>H</Initials><AffiliationInfo><Affiliation>State Key Laboratory for Managing Biotic and Chemical Threats to the Quality and Safety of Agro-Products/Key Laboratory of Detection for Pesticide Residues and Control of Zhejiang, Institute of Agro-Product Safety and Nutrition, Zhejiang Academy of Agricultural Sciences, Hangzhou 310021, P. R. China.</Affiliation></AffiliationInfo><AffiliationInfo><Affiliation>Agricultural Ministry Key Laboratory for Pesticide Residue Detection, Hangzhou 310021, P. R. China.</Affiliation></AffiliationInfo></Author><Author ValidYN="Y"><LastName>Qi</LastName><ForeName>Peipei</ForeName><Initials>P</Initials><AffiliationInfo><Affiliation>State Key Laboratory for Managing Biotic and Chemical Threats to the Quality and Safety of Agro-Products/Key Laboratory of Detection for Pesticide Residues and Control of Zhejiang, Institute of Agro-Product Safety and Nutrition, Zhejiang Academy of Agricultural Sciences, Hangzhou 310021, P. R. China.</Affiliation></AffiliationInfo><AffiliationInfo><Affiliation>Agricultural Ministry Key Laboratory for Pesticide Residue Detection, Hangzhou 310021, P. R. China.</Affiliation></AffiliationInfo></Author><Author ValidYN="Y"><LastName>Wang</LastName><ForeName>Zhiwei</ForeName><Initials>Z</Initials><AffiliationInfo><Affiliation>State Key Laboratory for Managing Biotic and Chemical Threats to the Quality and Safety of Agro-Products/Key Laboratory of Detection for Pesticide Residues and Control of Zhejiang, Institute of Agro-Product Safety and Nutrition, Zhejiang Academy of Agricultural Sciences, Hangzhou 310021, P. R. China.</Affiliation></AffiliationInfo><AffiliationInfo><Affiliation>Agricultural Ministry Key Laboratory for Pesticide Residue Detection, Hangzhou 310021, P. R. China.</Affiliation></AffiliationInfo></Author><Author ValidYN="Y"><LastName>Liu</LastName><ForeName>Zhenzhen</ForeName><Initials>Z</Initials><AffiliationInfo><Affiliation>State Key Laboratory for Managing Biotic and Chemical Threats to the Quality and Safety of Agro-Products/Key Laboratory of Detection for Pesticide Residues and Control of Zhejiang, Institute of Agro-Product Safety and Nutrition, Zhejiang Academy of Agricultural Sciences, Hangzhou 310021, P. R. China.</Affiliation></AffiliationInfo><AffiliationInfo><Affiliation>Agricultural Ministry Key Laboratory for Pesticide Residue Detection, Hangzhou 310021, P. R. China.</Affiliation></AffiliationInfo></Author><Author ValidYN="Y"><LastName>Di</LastName><ForeName>Shanshan</ForeName><Initials>S</Initials><Identifier Source="ORCID">0009-0002-1343-5268</Identifier><AffiliationInfo><Affiliation>State Key Laboratory for Managing Biotic and Chemical Threats to the Quality and Safety of Agro-Products/Key Laboratory of Detection for Pesticide Residues and Control of Zhejiang, Institute of Agro-Product Safety and Nutrition, Zhejiang Academy of Agricultural Sciences, Hangzhou 310021, P. R. China.</Affiliation></AffiliationInfo><AffiliationInfo><Affiliation>Agricultural Ministry Key Laboratory for Pesticide Residue Detection, Hangzhou 310021, P. R. China.</Affiliation></AffiliationInfo></Author></AuthorList><Language>eng</Language><PublicationTypeList><PublicationType UI="D016428">Journal Article</PublicationType></PublicationTypeList><ArticleDate DateType="Electronic"><Year>2024</Year><Month>09</Month><Day>25</Day></ArticleDate></Article><MedlineJournalInfo><Country>United States</Country><MedlineTA>J Agric Food Chem</MedlineTA><NlmUniqueID>0374755</NlmUniqueID><ISSNLinking>0021-8561</ISSNLinking></MedlineJournalInfo><ChemicalList><Chemical><RegistryNumber>0</RegistryNumber><NameOfSubstance UI="D005659">Fungicides, Industrial</NameOfSubstance></Chemical><Chemical><RegistryNumber>0</RegistryNumber><NameOfSubstance UI="D011725">Pyridines</NameOfSubstance></Chemical><Chemical><RegistryNumber>0</RegistryNumber><NameOfSubstance UI="C558633">3-(difluoromethyl)-1-methyl-N-(1,2,3,4-tetrahydro-9-isopropyl-1,4-methanonaphthalen-5-yl)pyrazole-4-carboxamide</NameOfSubstance></Chemical><Chemical><RegistryNumber>0</RegistryNumber><NameOfSubstance UI="D009636">Norbornanes</NameOfSubstance></Chemical><Chemical><RegistryNumber>0</RegistryNumber><NameOfSubstance UI="D011720">Pyrazoles</NameOfSubstance></Chemical></ChemicalList><CitationSubset>IM</CitationSubset><MeshHeadingList><MeshHeading><DescriptorName UI="D005659" MajorTopicYN="Y">Fungicides, Industrial</DescriptorName><QualifierName UI="Q000737" MajorTopicYN="N">chemistry</QualifierName><QualifierName UI="Q000633" MajorTopicYN="N">toxicity</QualifierName></MeshHeading><MeshHeading><DescriptorName UI="D005638" MajorTopicYN="Y">Fruit</DescriptorName><QualifierName UI="Q000737" MajorTopicYN="N">chemistry</QualifierName></MeshHeading><MeshHeading><DescriptorName UI="D014675" MajorTopicYN="Y">Vegetables</DescriptorName><QualifierName UI="Q000737" MajorTopicYN="N">chemistry</QualifierName></MeshHeading><MeshHeading><DescriptorName UI="D000818" MajorTopicYN="N">Animals</DescriptorName></MeshHeading><MeshHeading><DescriptorName UI="D013237" MajorTopicYN="N">Stereoisomerism</DescriptorName></MeshHeading><MeshHeading><DescriptorName UI="D015027" MajorTopicYN="Y">Zebrafish</DescriptorName></MeshHeading><MeshHeading><DescriptorName UI="D005506" MajorTopicYN="N">Food Contamination</DescriptorName><QualifierName UI="Q000032" MajorTopicYN="N">analysis</QualifierName></MeshHeading><MeshHeading><DescriptorName UI="D018570" MajorTopicYN="N">Risk Assessment</DescriptorName></MeshHeading><MeshHeading><DescriptorName UI="D027843" MajorTopicYN="N">Vitis</DescriptorName><QualifierName UI="Q000737" MajorTopicYN="N">chemistry</QualifierName></MeshHeading><MeshHeading><DescriptorName UI="D011725" MajorTopicYN="N">Pyridines</DescriptorName><QualifierName UI="Q000737" MajorTopicYN="N">chemistry</QualifierName><QualifierName UI="Q000633" MajorTopicYN="N">toxicity</QualifierName></MeshHeading><MeshHeading><DescriptorName UI="D000528" MajorTopicYN="N">Alternaria</DescriptorName><QualifierName UI="Q000378" MajorTopicYN="N">metabolism</QualifierName><QualifierName UI="Q000737" MajorTopicYN="N">chemistry</QualifierName><QualifierName UI="Q000187" MajorTopicYN="N">drug effects</QualifierName></MeshHeading><MeshHeading><DescriptorName UI="D006801" MajorTopicYN="N">Humans</DescriptorName></MeshHeading><MeshHeading><DescriptorName UI="D009636" MajorTopicYN="N">Norbornanes</DescriptorName></MeshHeading><MeshHeading><DescriptorName UI="D011720" MajorTopicYN="N">Pyrazoles</DescriptorName></MeshHeading></MeshHeadingList><KeywordList Owner="NOTNLM"><Keyword MajorTopicYN="N">acute toxicity</Keyword><Keyword MajorTopicYN="N">bioactivity</Keyword><Keyword MajorTopicYN="N">degradation</Keyword><Keyword MajorTopicYN="N">isopyrazam stereoisomers</Keyword><Keyword MajorTopicYN="N">stereoselectivity</Keyword></KeywordList></MedlineCitation><PubmedData><History><PubMedPubDate PubStatus="pubmed"><Year>2024</Year><Month>9</Month><Day>25</Day><Hour>22</Hour><Minute>18</Minute></PubMedPubDate><PubMedPubDate PubStatus="medline"><Year>2024</Year><Month>10</Month><Day>9</Day><Hour>7</Hour><Minute>22</Minute></PubMedPubDate><PubMedPubDate PubStatus="entrez"><Year>2024</Year><Month>9</Month><Day>25</Day><Hour>14</Hour><Minute>12</Minute></PubMedPubDate></History><PublicationStatus>ppublish</PublicationStatus><ArticleIdList><ArticleId IdType="pubmed">39321313</ArticleId><ArticleId IdType="doi">10.1021/acs.jafc.4c05937</ArticleId></ArticleIdList></PubmedData></PubmedArticle>